{
"ZYH100001":"交易代码",
"ZYH100002":"收单参考编号",
"ZYH100003":"收单业务编号",
"ZYH100004":"购买日期",
"ZYH100006":"交易货币代码",
"ZYH100007":"商家名称",
"ZYH100008":"城市",
"ZYH100009":"国家代码",
"ZYH100010":"邮政编码",
"ZYH100011":"商户国家╱省代码",
"ZYH100012":"发卡机构控制号",
"ZYH100013":"请求原因代码",
"ZYH100014":"结算标志",
"ZYH100015":"国家偿还费",
"ZYH100016":"账户种类",
"ZYH100017":"调单请求ID",
"ZYH100018":"中央处理日期",
"ZYH100019":"偿还属性",
"ZYH100020":"传真号码",
"ZYH100021":"请求完成方式",
"ZYH100022":"已建立的完成方式",
"ZYH100023":"发卡机构清算币种",
"ZYH100024":"发卡机构清算金额",
"ZYH100025":"交易ID",
"ZYJ100001":"人工",
"ZYJ100002":"自动",
"ZYJ100003":"请输入请求原因代码",
"ZYJ100004":"VISA调单申请维护页面",
"ZYJ100005":"VISA调单申请查询页面"
}