{
	"YYH5400001": "Accounting Type Code",
	"YYH5400002": "Description",
	"YYH5400003": "Mapping Dimension1",
	"YYH5400004": "Mapping Dimension2",
	"YYH5400005": "Mapping Dimension3",
	"YYH5400006": "Mapping Dimension4",
	"YYH5400007": "Mapping Dimension5",
	"YYH5400008": "Mapping Dimensions",
	"YYH5400009": "Add mapping dimension",
	"YYH5400010": "Frame Member Code",
	"YYH5400011": "Frame Member Desc",
	"YYH5400012": "Accounting Type Code and Desc",
	"YYH5400013": "Accounting Rule Code",
	"YYH5400014": "Rule Code",
	"YYH5400015": "Accounting Object",
	"YYH5400016": "Sub Rule Type",
	"YYH5400017": "Bal Attribute",
	"YYH5400018": "Bal Type",
	"YYH5400019": "BCO Code",
	"YYH5400020": "Direction",
	"YYH5400021": "Send Account?",
	"YYH5400022": "Non-balance class",
	"YYH5400023": "Balance class",
	"YYH5400024": "Internal account",
	"YYH5400025": "Title",
	"YYH5400026": "None",
	"YYH5400027": "Principal",
	"YYH5400028": "Interest",
	"YYH5400029": "Fees",
	"YYH5400030": "Accounting rules Desc",
	"YYH5400031": "Information match",
	"YYH5400032": "Accounting BCO",
	"YYH5400033": "Sub-table number",
	"YYH5400034": "Accounting Engine Element 1",
	"YYH5400035": "Accounting Engine Element 2",
	"YYH5400036": "Details",
	"YYH5400037": "Accounting Engine Element Desc 1",
	"YYH5400038": "Accounting Engine Element Desc 2",
	"YYH5400039": "Asset Attributes",
	"YYH5400040": "Internal Account",
	"YYH5400041": "Lending Direction",
	"YYH5400042": "Currency",
	"YYH5400043": "Local currency",
	"YYH5400044": "Foreign currency",
	"YYH5400045": "Primary Scenario ID",
	"YYH5400046": "Sub-Scenario Seq.",
	"YYH5400047": "Reversal Flag",
	"YYH5400048": "Red Ink",
	"YYH5400049": "Accounting main scene Desc",
	"YYH5400050": "Rule Code1",
	"YYH5400051": "Rule Code2",
	"YYH5400052": "Rule Code3",
	"YYH5400053": "Rule Code4",
	"YYH5400054": "Rule Code5",
	"YYH5400055": "Add new accounting rule code",
	"YYH5400056": "Accounting Main Scene Desc",
	"YYH5400057": "Description",
	"YYH5400058": "Global Serial Number",
	"YYH5400059": "Accounting Flow Information",
	"YYH5400060": "Accounting Amount",
	"YYH5400061": "Atomic Action Number",
	"YYH5400062": "Amount Type Number",
	"YYH5400063": "Accounting Date",
	"YYH5400064": "Billing Date",
	"YYH5400065": "Account",
	"YYH5400066": "Accounting Type Number",
	"YYH5400067": "Product Object Code",
	"YYH5400068": "Business Type Code",
	"YYH5400069": "Transaction Institution",
	"YYH5400070": "Account Institution",
	"YYH5400071": "Transaction Summary",
	"YYH5400072": "Channel Code",
	"YYH5400073": "Accounting Status Code",
	"YYH5400074": "Accounting ID",
	"YYH5400075": "booking currency",
	"YYH5400076": "Bookkeeping currency decimal places",
	"YYH5400077": "Accounting Amount",
	"YYH5400078": "Processing Status",
	"YYH5400079": "balance change indicator",
	"YYH5400080": "Change",
	"YYH5400081": "No change",
	"YYH5400082":"Account accounting status",
	"YYH5400083":"Balance unit accounting status",
	"YYH5400084":"Currency indication",
	"YYH5400085":"Scene number",
	"YYH5400086":"Scene description",
	"YYH5400087":"Renminbi",
	"YYH5400088":"Dollar",
	"YYH5400089":"Multi asset processing identification",
	"YYH5400090":"Accounting scenario event number",
	"YYH5400091":"Accounting scenario event",
	"YYH5400092":"Accounting scenario events",
	"YYH5400093": "Bind Accounting Scenario",
	"YYH5400094":"Enable accounting status",
	"YYH5400095":"Original accounting status",
	"YYH5400096":"Target accounting status",
	"YYH5400097":"Enabling currencies",
	"YYH5400098":"Packet",
	"YYH5400099":"Transfer period",
	"YYH5400100":"buy-back",
	"YYH5400101":"Enable asset transition phase",
	"YYH5400102":"Transformation stage of original assets",
	"YYH5400103":"Target assets transformation stage",
	"YYH5400104": "Linkage income accounting rule code",
	"YYH5400105": "Linkage Tax Accounting Rule Code",
	"YYH5400106": "Binding accounting code for accounting scenario linkage income scenario",
	"YYH5400107": "Code for binding tax accounting rules in the accounting scenario",
	"YYH5400108": "Accounting Scene",
	"YYH5400109": "Optional accounting scenarios",
	"YYH5400110": "The selected accounting scenario",
	"YYH5400111": "Accounting Scene Number",
	"YYH5400112": "Description of Accounting Scene",
	"YYH5400113": "Subtable Description",
	"YYH5400114": "Sub-table of Codes for Linkage Income Accounting Rules",
	"YYH5400115": "Sub-table of linked tax accounting rules",
	"YYH5400116": "Sub-table of binding accounting rule code for binding accounting scenarios",
	"YYH5400117": "Sub-table of Codes for Linked Tax Accounting Rules for Accounting Scenarios",
	"YYH5400118": "Enable accounting status",
	"YYJ5400001": "Accounting type Setup",
	"YYJ5400003": "Accounting type Maintain",
	"YYJ5400004": "Confirm to delete accounting type",
	"YYJ5400005": "Only up to 5 mapping dimensions can be added!",
	"YYJ5400006": "The dimensions are duplicate",
	"YYJ5400007": "MODP-Product Object",
	"YYJ5400008": "MODT-business type",
	"YYJ5400009": "Accounting type mapping dimension instance setup",
	"YYJ5400010": "Accounting Type Mapping Dimension Instance Details",
	"YYJ5400011": "Maintain accounting type mapping dimension Instance",
	"YYJ5400012": "Confirm to delete accounting type mapping dimension instance",
	"YYJ5400013": "Accounting rules main-table Setup",
	"YYJ5400014": "Accounting rules main-table Details",
	"YYJ5400015": "Accounting rules main-table Maintain",
	"YYJ5400016": "Confirm to delete accounting rule",
	"YYJ5400017": "Please check to input all required fields",
	"YYJ5400018": "None",
	"YYJ5400019": "Principal",
	"YYJ5400020": "interest",
	"YYJ5400021": "Fees",
	"YYJ5400022": "Internal Account",
	"YYJ5400023": "Title",
	"YYJ5400024": "Non-balance class",
	"YYJ5400025": "balance class",
	"YYJ5400026": "Accounting Rules Sub-Table - Title Setup",
	"YYJ5400027": "Accounting Rules Sub-Table - Title Details",
	"YYJ5400028": "Accounting Rules Sub-Table - Title Maintain",
	"YYJ5400029": "Confirm to delete accounting rule sub-table",
	"YYJ5400030": "Accounting Rules Sub-Table - Internal Account Setup",
	"YYJ5400031": "Accounting Rules Sub-Table - Internal Account Details",
	"YYJ5400032": "Confirm to delete the internal account class accounting rule sub-table",
	"YYJ5400033": "Accounting Rules Sub-Table - Internal Account Maintain",
	"YYJ5400034": "Local currency",
	"YYJ5400035": "Foreign currency",
	"YYJ5400036": "Accounting main scene Setup",
	"YYJ5400037": "Accounting the main scene details",
	"YYJ5400038": "Red Ink",
	"YYJ5400039": "Blue Ink",
	"YYJ5400040": "The accounting rule code cannot be duplicate",
	"YYJ5400041": "Accounting main scene Maintain",
	"YYJ5400042": "Confirm to delete this accounting main scene",
	"YYJ5400043": "Only up to 5 accounting rules can be added!",
	"YYJ5400044": "Do you want to delete this scenario?",
	"YYJ5400045": "Accounting processing detail",
	"YYJ5400046":"Select accounting type code",
	"YYJ5400047":"Add a new sub-scenario",
	"YYJ5400048":"Auditor scene details",
	"YYJ5400049":"Audit sub-scenario modification"
}