{
"YYH1200001": "Fee Item ID",
"YYH1200002": "Fees category",
"YYH1200003": "Description",
"YYH1200004": "Instance dimension1",
"YYH1200005": "Instance dimension2",
"YYH1200006": "Instance dimension3",
"YYH1200007": "Instance dimension4",
"YYH1200008": "Instance dimension5",
"YYH1200009": "Annual fee",
"YYH1200010": "Late Fee",
"YYH1200011": "Over-limit fee",
"YYH1200012": "Cash fee",
"YYH1200013": "Transfer Fee",
"YYH1200014": "Service fee",
"YYH1200015": "Instalment fee",
"YYH1200016": "Business Type",
"YYH1200017": "Product object",
"YYH1200018": "Media Object",
"YYH1200019": "Currency",
"YYH1200020": "Channel",
"YYH1200021": "Period",
"YYH1200022": "Delinquency Level",
"YYH1200023": "Business Project",
"YYH1200024": "Event ID",
"YYH1200025": "Event Description",
"YYH1200026": "Event Accounting Direction",
"YYH1200027": "Operating Mode",
"YYH1200028": "Fee Item Code",
"YYH1200029": "Instance Code1",
"YYH1200030": "Instance Code2",
"YYH1200031": "Instance Code3",
"YYH1200032": "Instance Code4",
"YYH1200033": "Instance Code5",
"YYH1200034": "Fee Item",
"YYH1200035": "Fees Dimensions1 and Desc",
"YYH1200036": "Fees Dimensions2 and Desc",
"YYH1200037": "Embossing Fee",
"YYH1200038": "Charge method",
"YYH1200039": "Installment type",
"YYH1200040": "Charge method",
"YYH1200041": "Fee Instance Setup",
"YYH1200042": "Cancel acocunt manage fee",
"YYH1200043":"Trading source",
"YYH1200044":"Transaction source description",
"YYH1200045":"Source directory",
"YYH1200046":"Source directory description",
"YYJ1200001": "Annual Fee",
"YYJ1200002": "Late Fee",
"YYJ1200003": "Over-limit Fee",
"YYJ1200004": "Cash Fee",
"YYJ1200005": "Transfer Fee",
"YYJ1200006": "Service Fee",
"YYJ1200007": "Instalment Fee",
"YYJ1200008": "Fee item event details",
"YYJ1200009": "Fee Item Instances",
"YYJ1200010": "Value/Amount",
"YYJ1200011": "Percentage",
"YYJ1200012": "Full Amount",
"YYJ1200013": "Progressive Amount",
"YYJ1200014": "Permnent Credit Limit",
"YYJ1200015": "Fee Matrix",
"YYJ1200016": "Fee Item Instance Details",
"YYJ1200017": "Fee Item List",
"YYJ1200018": "Embossing Fee",
"YYJ1200019": "Cancel account manage fee"
}