{
"SQH900002":"客户号",
"SQH900003":"序号",
"SQH900004":"建立日期",
"SQH900005":"输入来源",
"SQH900006":"授权应答",
"SQH900007":"说明",
"SQH900008":"交易录入",
"SQH900009":"人工录入",
"SQH900010":"拒绝借记交易",
"SQH900011":"拒绝所有交易",
"SQH900012":"客户号",
"SQH900014":"建立日期",
"SQH900015":"输入来源",
"SQH900016":"授权应答",
"SQH900017":"说明",
"SQJ900001":"拒绝借记交易",
"SQJ900002":"拒绝所有交易",
"SQJ900003":"交易录入",
"SQJ900004":"人工录入",
"SQJ900005":"确认删除信息",
"SQJ900007":"修改信息",
"SQJ900008":"授权欺诈名单修改成功",
"SQJ900009":"授权欺诈名单修改失败",
"SQJ900010":"新增信息",
"SQJ900011":"授权欺诈名单新增成功",
"SQJ900012":"授权欺诈名单新增失败"
}